torchzq/__init__.py
torchzq/cli.py
torchzq/interrupt.py
torchzq/pbar.py
torchzq/runner.py
torchzq/saver.py
torchzq/scheduler.py
torchzq/typing.py
torchzq/utils.py
torchzq-1.0.8.data/scripts/tzq
torchzq-1.0.8.dist-info/LICENSE
torchzq-1.0.8.dist-info/METADATA
torchzq-1.0.8.dist-info/WHEEL
torchzq-1.0.8.dist-info/top_level.txt
torchzq-1.0.8.dist-info/RECORD
