Metadata-Version: 2.1
Name: torchzq
Version: 1.0.8
Summary: TorchZQ: A simple PyTorch experiment runner.
Home-page: https://github.com/enhuiz/torchzq
Author: enhuiz
Author-email: niuzhe.nz@outlook.com
License: UNKNOWN
Platform: UNKNOWN
Requires-Python: >=3.6.0
Requires-Dist: torch
Requires-Dist: zouqi (==1.0.8)
Requires-Dist: pyyaml
Requires-Dist: tqdm
Requires-Dist: pandas
Requires-Dist: torchvision
Requires-Dist: natsort
Requires-Dist: deprecated
